dlm/DLM.py
dlm/DLM_Compute_Model.py
dlm/DLM_Memory_Model.py
dlm/__init__.py
dynamic_learning_model-3.5.2.dist-info/licenses/LICENSE
dynamic_learning_model-3.5.2.dist-info/METADATA
dynamic_learning_model-3.5.2.dist-info/WHEEL
dynamic_learning_model-3.5.2.dist-info/top_level.txt
dynamic_learning_model-3.5.2.dist-info/RECORD
