Metadata-Version: 2.4
Name: dynamic-learning-model
Version: 3.5.2
Summary: A Dynamic Learning Model for processing NLP queries using hybrid AI and reasoning.
Home-page: https://github.com/VigneshT24/Dynamic_Learning_Model
Author: Vignesh Thondikulam
Author-email: vignesh.tho2006@gmail.com
License: MIT
Classifier: Programming Language :: Python :: 3
Classifier: Operating System :: OS Independent
Classifier: License :: OSI Approved :: MIT License
Requires-Python: >=3.12,<3.13
License-File: LICENSE
Requires-Dist: nltk
Requires-Dist: spacy
Requires-Dist: better_profanity
Requires-Dist: word2number
Requires-Dist: transformers
Requires-Dist: hf_xet
Dynamic: author
Dynamic: author-email
Dynamic: classifier
Dynamic: description
Dynamic: description-content-type
Dynamic: home-page
Dynamic: license
Dynamic: license-file
Dynamic: requires-dist
Dynamic: requires-python
Dynamic: summary
